capstone/m680x_const.py
capstone/sysz_const.py
capstone/bpf.py
capstone/tricore.py
capstone/evm.py
capstone/mips_const.py
capstone/sparc.py
capstone/sh_const.py
capstone/sparc_const.py
capstone/xcore.py
capstone/mos65xx_const.py
capstone/arm64.py
capstone/m680x.py
capstone/sh.py
capstone/riscv.py
capstone/ppc.py
capstone/__init__.py
capstone/tricore_const.py
capstone/riscv_const.py
capstone/mos65xx.py
capstone/arm.py
capstone/systemz.py
capstone/mips.py
capstone/arm64_const.py
capstone/m68k_const.py
capstone/wasm.py
capstone/bpf_const.py
capstone/x86_const.py
capstone/tms320c64x_const.py
capstone/xcore_const.py
capstone/x86.py
capstone/m68k.py
capstone/wasm_const.py
capstone/ppc_const.py
capstone/arm_const.py
capstone/tms320c64x.py
capstone/evm_const.py
capstone/include/capstone/capstone.h
capstone/include/capstone/mips.h
capstone/include/capstone/sparc.h
capstone/include/capstone/systemz.h
capstone/include/capstone/m68k.h
capstone/include/capstone/sh.h
capstone/include/capstone/arm.h
capstone/include/capstone/bpf.h
capstone/include/capstone/mos65xx.h
capstone/include/capstone/evm.h
capstone/include/capstone/x86.h
capstone/include/capstone/wasm.h
capstone/include/capstone/tricore.h
capstone/include/capstone/ppc.h
capstone/include/capstone/arm64.h
capstone/include/capstone/xcore.h
capstone/include/capstone/riscv.h
capstone/include/capstone/m680x.h
capstone/include/capstone/platform.h
capstone/include/capstone/tms320c64x.h
capstone/lib/libcapstone.dylib
capstone-5.0.5.dist-info/RECORD
capstone-5.0.5.dist-info/WHEEL
capstone-5.0.5.dist-info/top_level.txt
capstone-5.0.5.dist-info/LICENSE.TXT
capstone-5.0.5.dist-info/METADATA
