Metadata-Version: 2.1
Name: capstone
Version: 5.0.5
Summary: Capstone disassembly engine
Home-page: https://www.capstone-engine.org
Author: Nguyen Anh Quynh
Author-email: aquynh@gmail.com
Classifier: License :: OSI Approved :: BSD License
Classifier: Programming Language :: Python :: 3
Provides: capstone
Requires-Python: >=3.8
License-File: LICENSE.TXT
Requires-Dist: importlib-resources ; python_version < "3.9"
